[
    [
        "Week 01 Graded Problem Task 2",
        "46e45e1fc5e24dd2b9e8a93382e97f5b",
        1,
        {}
    ],
    [
        "Week 02 Graded Problem Task 1",
        "67f04dce356846219650e2514958f048",
        5,
        {}
    ],
    [
        "Week 02 Graded Problem Task 2 ",
        "d3c1c1156dca420789b8bc0c833bf34a",
        1,
        {"variable":1}
    ],
    [
        "Week 02 Graded Problem Task 3",
        "821bc15e0bed4e179ddc1c802b313eec",
        1,
        {"operator":1}
    ],
    [
        "Week 02 Graded Problem Task 4",
        "27a9876d7b714ae2b190e085857f4663",
        1,
        {"primitive_type":1}
    ],
    [
        "Week 03 Graded Problem Task 1",
        "d5146af552274e4fb0527e97365b970c",
        2,
        {"primitive_type":1}
    ],
    [
        "Week 03 Graded Problem Task 2",
        "6860730d8ab84d3cab8fb0f2351182e2",
        1,
        {}
    ],
    [
        "Week 03 Graded Problem Task 3A",
        "013d3f1c652143149dc60f4e818b6982",
        1,
        {}
    ],
    [
        "Week 03 Graded Problem Task 3B",
        "478f5f696e2649ae92dcc7a706e03f22",
        1,
        {}
    ],
    [
        "Week 04 Graded Problem Task 1",
        "5e4d503eb8084cca9f8ebf5397921420",
        1,
        {"object_class":0.4,"instance_variable":0.3,"method":0.3}
    ],
    [
        "Week 04 Graded Problem Task 2",
        "cb4951aacaf648af88111b92d51440a4",
        1,
        {"primitive_type":1}
    ],
    [
        "Week 04 Graded Problem Task 3",
        "180f93865c8b40d6a06f6dca6d2bf741",
        1,
        {"branch":1}
    ],
    [
        "Week 04 Graded Problem Task 4",
        "2879f5a8c65745bc8e945bb9ee7e798a",
        1,
        {"branch":1}
    ],
    [
        "Week 05 Graded Problem Task 1",
        "0792a1e4ce5c428eafbb9467566c7a1c",
        1,
        {"loop":1}
    ],
    [
        "Week 05 Graded Problem Task 2",
        "d1dfc14002cc41aab7a6cb31c3b6aa18",
        1,
        {"operator":1}
    ],
    [
        "Week 05 Graded Problem Task 4",
        "b80ac7b29ad74e71bc334c2b3a072315",
        1,
        {"loop":1}
    ],
    [
        "Week 05 Graded Problem Task 5",
        "29ad9230a63f45eea3f5a325b33d2393",
        1,
        {"loop":1}
    ],
    [
        "Week 05 Graded Task 3",
        "d8600cf2a37a4f72a0aa4f254ee48455",
        1,
        {"primitive_type":1}
    ],
    [
        "Week 06 Graded Problem Task 1 ",
        "b45eb7410f12464ca3ba317d3fe46090",
        1,
        {"array":1}
    ],
    [
        "Week 06 Graded Problem Task 2",
        "662484c514da42fea6a0a3780cec52f8",
        1,
        {"array":1}
    ],
    [
        "Week 06 Graded Problem Task 3",
        "c1843fce4a3d42bab62f4a3c73ac6578",
        1,
        {"array":1}
    ],
    [
        "Week 06 Graded Problem Task 4",
        "591af8ce4e544c2aa1f41fcf9125930f",
        1,
        {}
    ],
    [
        "Week 06 Graded Problem Task 5",
        "17333909316240a0b59c679ab6c7ede1",
        1,
        {"nd_array":1}
    ],
    [
        "Week 06 Graded Problem Task 6",
        "8a899a153c85442793502aacb6d8aaac",
        1,
        {"nd_array":1}
    ],
    [
        "Week 07 Graded Problem Task 1",
        "0eccc6a390844ac9b8d5a92eef410848",
        1,
        {"string":1}
    ],
    [
        "Week 07 Graded Problem Task 2",
        "265841130b8040bda63f205373944857",
        1,
        {"string":1}
    ],
    [
        "Week 07 Graded Problem Task 3",
        "050ab84aae0840c8863053c6bd287f94",
        1,
        {"string":0.5,"loop":0.2,"method":0.3}
    ],
    [
        "Week 07 Graded Problem Task 4",
        "7d10011449bf4ce7b07df4fbe8422472",
        1,
        {"string":0.8,"method":0.2}
    ],
    [
        "Week 07 Graded Problem Task 4 (for reference only)",
        "9f9556e595394d3ebc68b6cbf6e8c6eb",
        0,
        {}
    ],
    [
        "Week 08 Graded Problem Task 1",
        "c9fec2c277df4bb89862b4f5f913b910",
        1,
        {"object_class":0.5,"method":0.5}
    ],
    [
        "Week 08 Graded Problem Task 2",
        "7f03405fb68145bf9ca94c2f6a2b250b",
        1,
        {"method":1}
    ],
    [
        "Week 08 Graded Problem Task 3",
        "f317883654264eb2ba5485e991bdeac3",
        1,
        {"method":1}
    ],
    [
        "Week 09 Graded Problem Task 1",
        "a7b066155ce5435984635e11f8a666f3",
        1,
        {"recursion":1}
    ],
    [
        "Week 09 Graded Problem Task 2",
        "f819e50f696a48678cad2fadd4b5f485",
        1,
        {"recursion":1}
    ],
    [
        "Week 09 Graded Problem Task 3",
        "6031b3c8f6cd4cf1a04d009273e298db",
        1,
        {"recursion":1}
    ],
    [
        "Week 09 Graded Problem Task 4",
        "6d6a425cf0da4a268f637fb33572d1a3",
        1,
        {"recursion":1}
    ],
    [
        "Week 10 Graded Problem Task 1",
        "a1268f53b50c45fe9b7fb62e2d06a989",
        1,
        {}
    ],
    [
        "Week 10 Graded Problem Task 2",
        "18fb0ef71659465db38b88dee53d8064",
        5,
        {}
    ]
]
